t_reporting_sdk/__init__.py
t_reporting_sdk/config.py
t_reporting_sdk/default_dependencies.py
t_reporting_sdk/domain/agent_runs/__init__.py
t_reporting_sdk/domain/agent_runs/fakers.py
t_reporting_sdk/domain/agent_runs/models.py
t_reporting_sdk/domain/cam_records/__init__.py
t_reporting_sdk/domain/cam_records/fakers.py
t_reporting_sdk/domain/cam_records/models.py
t_reporting_sdk/domain/eva_records/__init__.py
t_reporting_sdk/domain/eva_records/fakers.py
t_reporting_sdk/domain/eva_records/models.py
t_reporting_sdk/domain/paula_records/__init__.py
t_reporting_sdk/domain/paula_records/fakers.py
t_reporting_sdk/domain/paula_records/models.py
t_reporting_sdk/repositories/__init__.py
t_reporting_sdk/repositories/agent_runs/repository.py
t_reporting_sdk/repositories/api_clients/__init__.py
t_reporting_sdk/repositories/api_clients/fabric/__init__.py
t_reporting_sdk/repositories/api_clients/fabric/auth.py
t_reporting_sdk/repositories/api_clients/fabric/client.py
t_reporting_sdk/repositories/cam_records/repository.py
t_reporting_sdk/repositories/eva_records/repository.py
t_reporting_sdk/repositories/paula_records/repository.py
t_reporting_sdk/sdk/__init__.py
t_reporting_sdk/sdk/cam/cam_reporter.py
t_reporting_sdk/sdk/eva/eva_reporter.py
t_reporting_sdk/sdk/paula/__init__.py
t_reporting_sdk/sdk/paula/paula_reporter.py
t_reporting_sdk-0.6.1.dist-info/METADATA
t_reporting_sdk-0.6.1.dist-info/WHEEL
t_reporting_sdk-0.6.1.dist-info/top_level.txt
t_reporting_sdk-0.6.1.dist-info/RECORD
